chartreuse/__init__.py
chartreuse/chartreuse.py
chartreuse/chartreuse_upgrade.py
chartreuse/config_loader.py
chartreuse/utils/__init__.py
chartreuse/utils/alembic_migration_helper.py
chartreuse-6.2.0.dist-info/licenses/LICENCE.md
chartreuse-6.2.0.dist-info/METADATA
chartreuse-6.2.0.dist-info/WHEEL
chartreuse-6.2.0.dist-info/entry_points.txt
chartreuse-6.2.0.dist-info/top_level.txt
chartreuse-6.2.0.dist-info/zip-safe
chartreuse-6.2.0.dist-info/RECORD
