Metadata-Version: 2.4
Name: chartreuse
Version: 6.2.0
Summary: Helper for Alembic migrations within Kubernetes.
Author-email: wiremind <dev@wiremind.io>
License-Expression: LGPL-3.0-or-later
Project-URL: github, https://github.com/wiremind/chartreuse
Requires-Python: >=3.11.0
License-File: LICENCE.md
Requires-Dist: alembic
Requires-Dist: psycopg2
Requires-Dist: pydantic>=2.0.0
Requires-Dist: PyYAML
Requires-Dist: wiremind-kubernetes~=7.0
Provides-Extra: test
Requires-Dist: mock; extra == "test"
Requires-Dist: pytest; extra == "test"
Requires-Dist: pytest-mock; extra == "test"
Provides-Extra: ruff
Requires-Dist: ruff; extra == "ruff"
Provides-Extra: dev
Requires-Dist: ruff; extra == "dev"
Requires-Dist: pip-tools; extra == "dev"
Requires-Dist: mock; extra == "dev"
Requires-Dist: pytest; extra == "dev"
Requires-Dist: pytest-mock; extra == "dev"
Dynamic: license-file
